<?xml version="1.0" encoding="utf-8" ?>
<XnaContent>
	<Item>
		<ObjectType>Block</ObjectType>
		<ObjectName>LockedDoorLeft</ObjectName>
		<PositionX>224</PositionX>
		<PositionY>72</PositionY>
	</Item>
	<Item>
		<ObjectType>Block</ObjectType>
		<ObjectName>OpenDoorDown</ObjectName>
		<PositionX>112</PositionX>
		<PositionY>0</PositionY>
	</Item>
	<Item>
		<ObjectType>Block</ObjectType>
		<ObjectName>OpenDoorRight</ObjectName>
		<PositionX>0</PositionX>
		<PositionY>72</PositionY>
	</Item>
	<Item>
		<ObjectType>Block</ObjectType>
		<ObjectName>PushBlock</ObjectName>
		<PositionX>112</PositionX>
		<PositionY>80</PositionY>
	</Item>
	<Item>
		<ObjectType>Enemy</ObjectType>
		<ObjectName>Gel</ObjectName>
		<PositionX>100</PositionX>
		<PositionY>51</PositionY>
	</Item>
	<Item>
		<ObjectType>Enemy</ObjectType>
		<ObjectName>Gel</ObjectName>
		<PositionX>180</PositionX>
		<PositionY>51</PositionY>
	</Item>
	<Item>
		<ObjectType>Enemy</ObjectType>
		<ObjectName>Gel</ObjectName>
		<PositionX>68</PositionX>
		<PositionY>67</PositionY>
	</Item>
</XnaContent>